[
  {
    "colSpan": 4,
    "defaultValue": null,
    "displayCondition": null,
    "fieldGroup": null,
    "fieldName": "直、間接人員 (隱藏)",
    "fieldOptions": [],
    "fieldType": "dxTextBox",
    "formFieldId": "attend-absent-leave-form-by-html-983",
    "infoDisplayCondition": false,
    "isReadonly": true,
    "isVisible": false,
    "parentField": null,
    "relatedFormsExtend": "",
    "relatedSource": null,
    "sort": null,
    "specialFieldCode": "983",
    "translation": []
  },
  {
    "colSpan": 4,
    "defaultValue": null,
    "displayCondition": null,
    "fieldGroup": null,
    "fieldName": "成本部門 (隱藏)",
    "fieldOptions": [],
    "fieldType": "dxTextBox",
    "formFieldId": "attend-absent-leave-form-by-html-984",
    "infoDisplayCondition": false,
    "isReadonly": true,
    "isVisible": false,
    "parentField": null,
    "relatedFormsExtend": "OrgEmp",
    "relatedSource": null,
    "sort": null,
    "specialFieldCode": "984",
    "translation": []
  },
  {
    "colSpan": 4,
    "defaultValue": null,
    "displayCondition": null,
    "fieldGroup": null,
    "fieldName": "編織部門 (隱藏)",
    "fieldOptions": [],
    "fieldType": "dxTextBox",
    "formFieldId": "attend-absent-leave-form-by-html-985",
    "infoDisplayCondition": false,
    "isVisible": false,
    "parentField": null,
    "relatedFormsExtend": "OrgEmp",
    "relatedSource": null,
    "sort": null,
    "specialFieldCode": "985",
    "translation": []
  },
  {
    "colSpan": 4,
    "defaultValue": null,
    "displayCondition": null,
    "fieldGroup": null,
    "fieldName": "公司別 (隱藏)",
    "fieldOptions": [],
    "fieldType": "dxTextBox",
    "formFieldId": "attend-absent-leave-form-by-html-986",
    "infoDisplayCondition": false,
    "isReadonly": true,
    "isVisible": false,
    "parentField": null,
    "relatedFormsExtend": "",
    "relatedSource": null,
    "sort": null,
    "specialFieldCode": "986",
    "translation": []
  },
  {
    "colSpan": 4,
    "defaultValue": null,
    "displayCondition": null,
    "fieldGroup": null,
    "fieldName": "工作地 (隱藏)",
    "fieldOptions": [],
    "fieldType": "dxTextBox",
    "formFieldId": "attend-absent-leave-form-by-html-987",
    "infoDisplayCondition": false,
    "isReadonly": true,
    "isVisible": false,
    "parentField": null,
    "relatedFormsExtend": "",
    "relatedSource": null,
    "sort": null,
    "specialFieldCode": "987",
    "translation": []
  },
  {
    "colSpan": 4,
    "defaultValue": null,
    "displayCondition": null,
    "fieldGroup": null,
    "fieldName": "職等 (隱藏)",
    "fieldOptions": [],
    "fieldType": "dxTextBox",
    "formFieldId": "attend-absent-leave-form-by-html-988",
    "infoDisplayCondition": false,
    "isReadonly": true,
    "isVisible": false,
    "parentField": null,
    "relatedFormsExtend": "",
    "relatedSource": null,
    "sort": null,
    "specialFieldCode": "988",
    "translation": []
  },
  {
    "colSpan": 4,
    "defaultValue": null,
    "displayCondition": null,
    "fieldGroup": null,
    "fieldName": "職級 (隱藏)",
    "fieldOptions": [],
    "fieldType": "dxTextBox",
    "formFieldId": "attend-absent-leave-form-by-html-989",
    "infoDisplayCondition": false,
    "isReadonly": true,
    "isVisible": false,
    "parentField": null,
    "relatedFormsExtend": "",
    "relatedSource": null,
    "sort": null,
    "specialFieldCode": "989",
    "translation": []
  }
]
